csvcompare
