Metadata-Version: 1.1
Name: csvcompare
Version: 0.2.2
Summary: CSV file diff and comparison
Home-page: http://www.grantjenks.com/docs/csvcompare/
Author: Grant Jenks
Author-email: contact@grantjenks.com
License: Copyright 2015 Grant Jenks
